kraken/wrapper/__init__.py
kraken/wrapper/_config.py
kraken/wrapper/_option_sets.py
kraken/wrapper/main.py
kraken/wrapper/py.typed
kraken/wrapper/uv_venv.py
kraken/wrapper/venv_manager.py
kraken_wrapper-0.50.2.dist-info/METADATA
kraken_wrapper-0.50.2.dist-info/WHEEL
kraken_wrapper-0.50.2.dist-info/entry_points.txt
kraken_wrapper-0.50.2.dist-info/RECORD
